README.md
setup.py
src/AWSTextSummaryJassi.egg-info/PKG-INFO
src/AWSTextSummaryJassi.egg-info/SOURCES.txt
src/AWSTextSummaryJassi.egg-info/dependency_links.txt
src/AWSTextSummaryJassi.egg-info/top_level.txt
src/AwstextSummaryJassi07/__init__.py
src/AwstextSummaryJassi07/config/__init__.py
src/AwstextSummaryJassi07/config/configuration.py
src/AwstextSummaryJassi07/conponents/__init__.py
src/AwstextSummaryJassi07/conponents/data_ingestion.py
src/AwstextSummaryJassi07/conponents/data_transformation.py
src/AwstextSummaryJassi07/conponents/data_validation.py
src/AwstextSummaryJassi07/conponents/model_evaluation.py
src/AwstextSummaryJassi07/conponents/model_trainer.py
src/AwstextSummaryJassi07/constants/__init__.py
src/AwstextSummaryJassi07/entity/__init__.py
src/AwstextSummaryJassi07/logging/__init__.py
src/AwstextSummaryJassi07/pipeline/__init__.py
src/AwstextSummaryJassi07/pipeline/prediction.py
src/AwstextSummaryJassi07/pipeline/stage_01_data_ingestion.py
src/AwstextSummaryJassi07/pipeline/stage_02_data_validation.py
src/AwstextSummaryJassi07/pipeline/stage_03_data_transformation.py
src/AwstextSummaryJassi07/pipeline/stage_04_model_trainer.py
src/AwstextSummaryJassi07/pipeline/stage_05_model_evaluation.py
src/AwstextSummaryJassi07/utils/__init__.py
src/AwstextSummaryJassi07/utils/common.py