Metadata-Version: 2.1
Name: AWSTextSummaryJassi
Version: 0.0.0
Summary: A small python package for NLP app
Home-page: https://github.com/Jaspreet-Singh619/Text-Summarizer-Project
Author: Jaspreet-Singh619
Author-email: jaspreetsingh6194056@gmail.com
Project-URL: Bug Tracker, https://github.com/Jaspreet-Singh619/Text-Summarizer-Project/issues
